forecast_tool/__init__.py
forecast_tool/forecast_plot.py
forecast_tool-0.0.3.dist-info/LICENSE
forecast_tool-0.0.3.dist-info/METADATA
forecast_tool-0.0.3.dist-info/WHEEL
forecast_tool-0.0.3.dist-info/top_level.txt
forecast_tool-0.0.3.dist-info/RECORD
