Metadata-Version: 2.1
Name: forecast-tool
Version: 0.0.3
Summary: To easy plot forecasting through ARIMA model
Home-page: https://github.com/k-w-lee/forecast_vis
Author: Morris_Lee
Author-email: info.leekahwin@gmail.com
Project-URL: Bug Tracker, https://github.com/k-w-lee/forecast_vis/issues
Classifier: Programming Language :: Python :: 3
Classifier: License :: OSI Approved :: MIT License
Classifier: Operating System :: OS Independent
Requires-Python: >=3.6
License-File: LICENSE
